glmtree/__init__.py
glmtree/glmtree.py
glmtree/glmtreeboost.py
glmtree/mobtree.py
glmtree-0.2.6.dist-info/LICENSE
glmtree-0.2.6.dist-info/METADATA
glmtree-0.2.6.dist-info/WHEEL
glmtree-0.2.6.dist-info/top_level.txt
glmtree-0.2.6.dist-info/RECORD
