Metadata-Version: 2.1
Name: glmtree
Version: 0.2.6
Summary: Generalized linear model tree
Home-page: https://github.com/ZebinYang/GLMTree
Author: Zebin Yang
Author-email: yangzb2010@connect.hku.hk
License: GPL
Platform: UNKNOWN
Requires-Dist: matplotlib (>=3.1.3)
Requires-Dist: numpy (>=1.15.2)
Requires-Dist: scikit-learn (>=0.23.0)
